[
  {
    "id": 1,
    "category": "nature",
    "img": "https://images.amcnetworks.com/amc.com/wp-content/uploads/2015/04/cast_bb_700x1000_walter-white-lg.jpg",
    "isShow": true,
    "downloads": 574,
    "share": 76694,
    "saved": 594,
    "views": 99800,
    "likes": 796
  },
  {
    "id": 2,
    "category": "sky",
    "img": "https://images.amcnetworks.com/amc.com/wp-content/uploads/2015/04/cast_bb_700x1000_walter-white-lg.jpg",
    "isShow": true,
    "downloads": 776,
    "share": 775,
    "saved": 4574,
    "views": 95996,
    "likes": 95
  },
  {
    "id": 3,
    "category": "animal",
    "img": "https://images.amcnetworks.com/amc.com/wp-content/uploads/2015/04/cast_bb_700x1000_walter-white-lg.jpg",
    "isShow": true,
    "downloads": 829,
    "share": 138,
    "saved": 627,
    "views": 94729,
    "likes": 151
  },
  {
    "id": 4,
    "category": "nature",
    "img": "https://images.amcnetworks.com/amc.com/wp-content/uploads/2015/04/cast_bb_700x1000_walter-white-lg.jpg",
    "isShow": true,
    "downloads": 733,
    "share": 844,
    "saved": 642,
    "views": 10064,
    "likes": 844
  },
  {
    "id": 5,
    "category": "nature",
    "img": "https://images.amcnetworks.com/amc.com/wp-content/uploads/2015/04/cast_bb_700x1000_walter-white-lg.jpg",
    "isShow": true,
    "downloads": 732,
    "share": 7654,
    "saved": 132,
    "views": 67763,
    "likes": 152
  },
  {
    "id": 6,
    "category": "animal",
    "img": "https://images.amcnetworks.com/amc.com/wp-content/uploads/2015/04/cast_bb_700x1000_walter-white-lg.jpg",
    "isShow": true,
    "downloads": 829,
    "share": 941,
    "saved": 139,
    "views": 9949,
    "likes": 850
  },
  {
    "id": 7,
    "category": "sky",
    "img": "https://images.amcnetworks.com/amc.com/wp-content/uploads/2015/04/cast_bb_700x1000_walter-white-lg.jpg",
    "isShow": true,
    "downloads": 161,
    "share": 138,
    "saved": 149,
    "views": 6649,
    "likes": 128
  },
  {
    "id": 8,
    "category": "sky",
    "img": "https://images.amcnetworks.com/amc.com/wp-content/uploads/2015/04/cast_bb_700x1000_walter-white-lg.jpg",
    "isShow": true,
    "downloads": 99,
    "share": 80,
    "saved": 142,
    "views": 743,
    "likes": 132
  },
  {
    "id": 9,
    "category": "sky",
    "img": "https://images.amcnetworks.com/amc.com/wp-content/uploads/2015/04/cast_bb_700x1000_walter-white-lg.jpg",
    "isShow": true,
    "downloads": 157,
    "share": 158,
    "saved": 647,
    "views": 6648,
    "likes": 126
  },
  {
    "id": 10,
    "category": "nature",
    "img": "https://images.amcnetworks.com/amc.com/wp-content/uploads/2015/04/cast_bb_700x1000_walter-white-lg.jpg",
    "isShow": true,
    "downloads": 133,
    "share": 124,
    "saved": 112,
    "views": 7744,
    "likes": 113
  }
]